{
  "date": "March 24, 2026",
  "lastUpdated": "2026-03-24T18:00:00.000Z",
  "record": "30-16 (+11.0 units)",
  "betOfDay": {
    "sport": "NBA",
    "game": "Denver Nuggets @ Phoenix Suns",
    "time": "9:10 PM MT",
    "pick": "Denver Nuggets -6",
    "odds": "-110",
    "units": 2,
    "tag": "⭐ TOP PICK",
    "reasoning": "Jokic dominant, line at -6 with slight sharp movement toward Denver. Suns struggling at home."
  },
  "picks": [
    {
      "sport": "NBA",
      "game": "Denver Nuggets @ Phoenix Suns",
      "time": "9:10 PM MT",
      "pick": "Denver Nuggets -6",
      "odds": "-110",
      "units": 2,
      "tag": "⭐ TOP PICK",
      "reasoning": "Jokic dominant road favorite. Line -6 to -6.5 with sharp movement. Suns one of worst teams in West."
    },
    {
      "sport": "NBA",
      "game": "Orlando Magic @ Cleveland Cavaliers",
      "time": "6:10 PM MT",
      "pick": "Cleveland Cavaliers -10.5",
      "odds": "-110",
      "units": 1,
      "tag": "",
      "reasoning": "#1 seed East at home. Locked at -10.5 across all 8 books. Magic weak on road."
    },
    {
      "sport": "NBA",
      "game": "New Orleans Pelicans @ New York Knicks",
      "time": "5:44 PM MT",
      "pick": "New York Knicks -8.5",
      "odds": "-110",
      "units": 1,
      "tag": "",
      "reasoning": "Knicks at MSG vs worst team in West. Line -8.5 consensus."
    },
    {
      "sport": "NHL",
      "game": "San Jose Sharks @ Nashville Predators",
      "time": "6:05 PM MT",
      "pick": "Nashville Predators -1.5",
      "odds": "-110",
      "units": 1,
      "tag": "",
      "reasoning": "Sharks worst in NHL. Preds home puck-line value."
    }
  ],
  "injuries_flagged": [],
  "research": {
    "nba": "4 NBA picks today. Odds via The Odds API. Top pick: Denver Nuggets -6 road favorite with Jokic.",
    "nhl": "1 NHL pick: Nashville -1.5 vs San Jose (worst team in NHL)."
  }
}
